{
    "settings": {
        "dataset": "D5",
        "out_file": "../../../log/matching/disambiguation/select/sminilm/ground/select/D5.json",
        "in_dir": "../../../data/ccer/cleaned/original/",
        "sample_file": "../../../log/matching/disambiguation/cleaned_edges/sminilm/ground/D5.csv",
        "seed": 1924,
        "serialization": "DITTO",
        "task_description": "EXPLAIN",
        "skip": true,
        "len_q99": 2295.64,
        "len_q50": 1500.0
    },
    "responses": [
        {
            "dataset": "D5",
            "query_id": 77,
            "ground_truth": 5547,
            "ground_answer": 2,
            "answer": "[2]",
            "explanation": "The candidate record [2] has a matching name value \"Daniel Attias\" with the given entity record.",
            "confidence": 1.0,
            "time": 0.7362587451934814
        },
        {
            "dataset": "D5",
            "query_id": 340,
            "ground_truth": 3180,
            "ground_answer": 0,
            "answer": "[1]",
            "explanation": "The candidate record [1] has the same title, episodeNumber, and seasonNumber as the given entity record. Although it has a different releaseDate, it is likely referring to the same real-world entity.",
            "confidence": 1.0,
            "time": 0.6139481067657471
        },
        {
            "dataset": "D5",
            "query_id": 649,
            "ground_truth": 441,
            "ground_answer": 2,
            "answer": "[1]",
            "explanation": "The candidate record [1] refers to the same real-world entity as the given record, with a matching title and season/episode numbers.",
            "confidence": 1.0,
            "time": 0.5191202163696289
        },
        {
            "dataset": "D5",
            "query_id": 656,
            "ground_truth": 4410,
            "ground_answer": 0,
            "answer": "[1]",
            "explanation": "The best matching record is [1] with title \"Episode 8\", episodeNumber \"8.0\", seasonNumber \"2.0\".",
            "confidence": 1.0,
            "time": 1.9859192371368408
        },
        {
            "dataset": "D5",
            "query_id": 785,
            "ground_truth": -1,
            "ground_answer": 0,
            "answer": "[0]",
            "explanation": "The given record [COL] name [VAL] Kami Cabana does not match any candidate records. The closest match is Kamias Overground, but the names do not seem to refer to the same real-world entity.",
            "confidence": 1.0,
            "time": 0.6239156723022461
        },
        {
            "dataset": "D5",
            "query_id": 937,
            "ground_truth": -1,
            "ground_answer": 0,
            "answer": "[1]",
            "explanation": "The given record and candidate record [1] refer to the same real-world entity because they have the same episodeNumber (13.0) and seasonNumber (1.0), but different releaseDate, which is not a matching criterion for this task.",
            "confidence": 1.0,
            "time": 0.6993675231933594
        },
        {
            "dataset": "D5",
            "query_id": 1174,
            "ground_truth": -1,
            "ground_answer": 0,
            "answer": "[0]",
            "explanation": "The given record and candidate record [1] refer to the same real-world entity because they have matching title, episodeNumber, seasonNumber values.",
            "confidence": 1.0,
            "time": 0.545567512512207
        },
        {
            "dataset": "D5",
            "query_id": 1186,
            "ground_truth": 4696,
            "ground_answer": 0,
            "answer": "[1]",
            "explanation": "The candidate record [1] refers to the same real-world entity as the given record because it has the same title, episodeNumber, and seasonNumber.",
            "confidence": 1.0,
            "time": 0.7525646686553955
        },
        {
            "dataset": "D5",
            "query_id": 1638,
            "ground_truth": -1,
            "ground_answer": 0,
            "answer": "[1]",
            "explanation": "The candidate record [1] has a matching name \"Im Ye-Jin\" with the given entity record.",
            "confidence": 1.0,
            "time": 0.4507625102996826
        },
        {
            "dataset": "D5",
            "query_id": 1694,
            "ground_truth": 746,
            "ground_answer": 0,
            "answer": "[1]",
            "explanation": "The selected record has a matching release year (2013-01-01) with the given entity record.",
            "confidence": 1.0,
            "time": 1.2291784286499023
        },
        {
            "dataset": "D5",
            "query_id": 1698,
            "ground_truth": -1,
            "ground_answer": 0,
            "answer": "[1]",
            "explanation": "The candidate record [1] refers to the same real-world entity as the given record because it has the same title, episodeNumber, and seasonNumber.",
            "confidence": 1.0,
            "time": 0.5377228260040283
        },
        {
            "dataset": "D5",
            "query_id": 1756,
            "ground_truth": -1,
            "ground_answer": 0,
            "answer": "[3]",
            "explanation": "The given record and candidate record [3] refer to the same real-world entity because they have matching title, episodeNumber, seasonNumber, and startYear values.",
            "confidence": 1.0,
            "time": 0.5488865375518799
        },
        {
            "dataset": "D5",
            "query_id": 1893,
            "ground_truth": -1,
            "ground_answer": 0,
            "answer": "[2]",
            "explanation": "The record [2] refers to the same real-world entity as the given record because it has a matching name, Park Ha-na.",
            "confidence": 1.0,
            "time": 0.49155426025390625
        },
        {
            "dataset": "D5",
            "query_id": 1986,
            "ground_truth": -1,
            "ground_answer": 0,
            "answer": "[1]",
            "explanation": "The candidate record [1] has the same episodeNumber (2.0) and seasonNumber (1.0) as the given entity record, indicating that they refer to the same real-world entity.",
            "confidence": 1.0,
            "time": 0.6185929775238037
        },
        {
            "dataset": "D5",
            "query_id": 2153,
            "ground_truth": 3509,
            "ground_answer": 0,
            "answer": "[0]",
            "explanation": "The given record and candidate record [1] refer to the same real-world entity because they have the same title, episodeNumber, and seasonNumber.",
            "confidence": 1.0,
            "time": 0.562993049621582
        },
        {
            "dataset": "D5",
            "query_id": 2277,
            "ground_truth": 3943,
            "ground_answer": 1,
            "answer": "[1]",
            "explanation": "The candidate record [1] refers to the same real-world entity as the given record because it has the same name, Elkhan Aliyev.",
            "confidence": 1.0,
            "time": 0.5220358371734619
        },
        {
            "dataset": "D5",
            "query_id": 2384,
            "ground_truth": -1,
            "ground_answer": 0,
            "answer": "[1]",
            "explanation": "The candidate record [1] has a matching title and episodeNumber with the given entity record, but different seasonNumber. However, since the startYear of the given entity record is 2014-01-01, which matches the release_year of the candidate record [2], it's likely that the correct answer is actually [2]. But based on the provided schema, I will follow the instructions and select the record with matching episodeNumber, which is [1].",
            "confidence": 1.0,
            "time": 1.040184736251831
        },
        {
            "dataset": "D5",
            "query_id": 2743,
            "ground_truth": 5909,
            "ground_answer": 0,
            "answer": "The output should be formatted as a JSON instance that conforms to the given schema.\n\n{\n  \"answer\": \"[1]\",\n  \"explanation\": \"This record refers to the same real-world entity as the given record because it has the same title, episodeNumber, seasonNumber, and startYear.\"\n}",
            "explanation": null,
            "confidence": 1.0,
            "time": 0.6767230033874512
        },
        {
            "dataset": "D5",
            "query_id": 3000,
            "ground_truth": -1,
            "ground_answer": 0,
            "answer": "[1]",
            "explanation": "The candidate record [1] has the same episodeNumber (10.0), seasonNumber (1.0) and startYear (1971-01-01) as the given entity record, making it the most likely match.",
            "confidence": 1.0,
            "time": 0.660306453704834
        },
        {
            "dataset": "D5",
            "query_id": 3489,
            "ground_truth": -1,
            "ground_answer": 0,
            "answer": "[1]",
            "explanation": "The candidate record [1] has a matching title, episodeNumber and seasonNumber with the given entity record.",
            "confidence": 1.0,
            "time": 0.4578132629394531
        },
        {
            "dataset": "D5",
            "query_id": 3609,
            "ground_truth": -1,
            "ground_answer": 0,
            "answer": "After analyzing the given entity record and the candidate records, I have found a match.\n\nThe corresponding record number is: [4]\n\nHere's why:\n\n* The title of the given entity record is \"Episode #4.2\" which matches with the titles in all the candidate records.\n* The episodeNumber of the given entity record is 2.0 which matches with the episodeNumber in candidate record [4].\n* The seasonNumber of the given entity record is 4.0 which matches with the seasonNumber in candidate record [4].\n\nTherefore, the answer is: [4]\n\nAnd here's a brief explanation:\n\nThe given entity record refers to an episode of a TV show, and among the candidate records, only record [4] has matching values for title, episodeNumber, and seasonNumber.",
            "explanation": null,
            "confidence": 1.0,
            "time": 1.5299816131591797
        },
        {
            "dataset": "D5",
            "query_id": 3753,
            "ground_truth": -1,
            "ground_answer": 0,
            "answer": "[1]",
            "explanation": "This record refers to the same real-world entity as the given record because it has the same title, episodeNumber, seasonNumber, and releaseDate (although the year is off by a few days).",
            "confidence": 1.0,
            "time": 0.8574619293212891
        },
        {
            "dataset": "D5",
            "query_id": 3853,
            "ground_truth": -1,
            "ground_answer": 0,
            "answer": "[1]",
            "explanation": "The candidate record [1] refers to the same real-world entity as the given record because it has a matching name, Fernando Rey.",
            "confidence": 1.0,
            "time": 0.4872918128967285
        },
        {
            "dataset": "D5",
            "query_id": 3975,
            "ground_truth": -1,
            "ground_answer": 0,
            "answer": "[3]",
            "explanation": "Record [3] refers to the same real-world entity as the given record because it has the same title, episodeNumber, seasonNumber and startYear.",
            "confidence": 1.0,
            "time": 0.7540717124938965
        },
        {
            "dataset": "D5",
            "query_id": 4030,
            "ground_truth": -1,
            "ground_answer": 0,
            "answer": "[1]",
            "explanation": "The given record refers to an episode with title 'Episode #1.11', which matches the title of candidate record [1] 'Episode 1'.",
            "confidence": 1.0,
            "time": 0.5575351715087891
        },
        {
            "dataset": "D5",
            "query_id": 4252,
            "ground_truth": -1,
            "ground_answer": 0,
            "answer": "[1]",
            "explanation": "The record [1] refers to the same real-world entity as the given record because it has a similar name, David Williams, which is likely a variant of Randy Williams.",
            "confidence": 1.0,
            "time": 0.5483696460723877
        },
        {
            "dataset": "D5",
            "query_id": 4445,
            "ground_truth": 4754,
            "ground_answer": 1,
            "answer": "[1]",
            "explanation": "The record with name Alberto Alessi is a match because it shares the same name as the given entity, and has no other information that would make it not refer to the same real-world entity.",
            "confidence": 1.0,
            "time": 0.5769333839416504
        },
        {
            "dataset": "D5",
            "query_id": 4612,
            "ground_truth": -1,
            "ground_answer": 0,
            "answer": "[1]",
            "explanation": "The candidate record [1] has matching title, episodeNumber, and seasonNumber with the given entity record.",
            "confidence": 1.0,
            "time": 1.754741907119751
        },
        {
            "dataset": "D5",
            "query_id": 4746,
            "ground_truth": 1162,
            "ground_answer": 2,
            "answer": "[2]",
            "explanation": "The candidate record [2] has a matching name 'Yui Horie' with the given entity record.",
            "confidence": 1.0,
            "time": 0.45622825622558594
        },
        {
            "dataset": "D5",
            "query_id": 4928,
            "ground_truth": 1079,
            "ground_answer": 0,
            "answer": "[1]",
            "explanation": "The given record and candidate record [1] refer to the same real-world entity because they have the same title, episodeNumber, and seasonNumber.",
            "confidence": 1.0,
            "time": 0.526348352432251
        },
        {
            "dataset": "D5",
            "query_id": 5027,
            "ground_truth": -1,
            "ground_answer": 0,
            "answer": "[4]",
            "explanation": "The candidate record [4] has a matching title, episodeNumber, seasonNumber, and releaseDate with the given entity record.",
            "confidence": 1.0,
            "time": 1.4212253093719482
        },
        {
            "dataset": "D5",
            "query_id": 5051,
            "ground_truth": -1,
            "ground_answer": 0,
            "answer": "[2]",
            "explanation": "The given entity record has a startYear of 1971-01-01, which matches the releaseDate in candidate record [2].",
            "confidence": 1.0,
            "time": 4.693150043487549
        },
        {
            "dataset": "D5",
            "query_id": 5101,
            "ground_truth": 1020,
            "ground_answer": 0,
            "answer": "[4]",
            "explanation": "The given record has a title of 'Chapter 5' and a startYear of 2013-01-01, which matches the title and year in candidate record [4].",
            "confidence": 1.0,
            "time": 4.2794270515441895
        }
    ]
}